virtualhome/__init__.py
virtualhome/simulation/__init__.py
virtualhome/simulation/environment/__init__.py
virtualhome/simulation/environment/__main__.py
virtualhome/simulation/environment/base_environment.py
virtualhome/simulation/environment/unity_environment.py
virtualhome/simulation/environment/utils.py
virtualhome/simulation/evolving_graph/__init__.py
virtualhome/simulation/evolving_graph/check_programs.py
virtualhome/simulation/evolving_graph/common.py
virtualhome/simulation/evolving_graph/environment.py
virtualhome/simulation/evolving_graph/execution.py
virtualhome/simulation/evolving_graph/preparation.py
virtualhome/simulation/evolving_graph/scripts.py
virtualhome/simulation/evolving_graph/utils.py
virtualhome/simulation/unity_simulator/__init__.py
virtualhome/simulation/unity_simulator/comm_unity.py
virtualhome/simulation/unity_simulator/communication.py
virtualhome/simulation/unity_simulator/utils_viz.py
virtualhome-2.3.0.dist-info/METADATA
virtualhome-2.3.0.dist-info/WHEEL
virtualhome-2.3.0.dist-info/top_level.txt
virtualhome-2.3.0.dist-info/RECORD
