Metadata-Version: 2.1
Name: virtualhome
Version: 2.3.0
Summary: Python API to communicate with the VirtualHome environment
Home-page: https://github.com/xavierpuigf/virtualhome
Author: Xavier Puig
Author-email: xavierpuig@csail.mit.edu
License: UNKNOWN
Project-URL: Documentation, https://virtualcity.readthedocs.io/en/latest/
Project-URL: Bug Tracker, https://github.com/ShuangLI59/virtualcity-python-api
Platform: UNKNOWN
Classifier: Programming Language :: Python :: 3
Classifier: License :: OSI Approved :: MIT License
Classifier: Operating System :: OS Independent
Requires-Python: >=3.8
Requires-Dist: certifi (==2019.3.9)
Requires-Dist: chardet (==3.0.4)
Requires-Dist: idna (==2.8)
Requires-Dist: matplotlib (>=3.4.2)
Requires-Dist: networkx (==2.3)
Requires-Dist: numpy (>=1.19.3)
Requires-Dist: opencv-python (==4.5.1.48)
Requires-Dist: pillow (>=8.3.1)
Requires-Dist: plotly (==3.10.0)
Requires-Dist: requests (>=1.21.0)
Requires-Dist: ipdb (==0.13.9)
Requires-Dist: termcolor (==1.1.0)
Requires-Dist: tqdm (==4.31.1)
Requires-Dist: urllib3 (>=1.24.3)
